gptautocli/__init__.py
gptautocli/apiHandler.py
gptautocli/behaviorConfig.py
gptautocli/chatBot.py
gptautocli/configHandler.py
gptautocli/getTerminal.py
gptautocli/historyManager.py
gptautocli/main.py
gptautocli/overwriteFileFunction.py
gptautocli/riskAssessment.py
gptautocli/shellSimulator.py
gptautocli/userInterface.py
gptautocli-0.1.2.5.dist-info/LICENSE
gptautocli-0.1.2.5.dist-info/METADATA
gptautocli-0.1.2.5.dist-info/WHEEL
gptautocli-0.1.2.5.dist-info/entry_points.txt
gptautocli-0.1.2.5.dist-info/top_level.txt
gptautocli-0.1.2.5.dist-info/RECORD
