Metadata-Version: 2.1
Name: gptautocli
Version: 0.1.2.5
Summary: Provides a conversational interface to the terminal, allowing you to run commands and perform tasks using natural language.
Home-page: https://github.com/BSchoolland/gptautocli
Author: Benjamin Schoolland
Author-email: bschoolland@gmail.com
License: UNKNOWN
Platform: UNKNOWN
Classifier: Programming Language :: Python :: 3
Classifier: License :: OSI Approved :: MIT License
Classifier: Operating System :: OS Independent
Requires-Python: >=3.6
License-File: LICENSE
Requires-Dist: colorama (==0.4.6)
Requires-Dist: openai (==1.52.0)
